ryanjohnsonsfirstpyapp/__init__.py
ryanjohnsonsfirstpyapp-0.0.2.dist-info/LICENSE.txt
ryanjohnsonsfirstpyapp-0.0.2.dist-info/METADATA
ryanjohnsonsfirstpyapp-0.0.2.dist-info/WHEEL
ryanjohnsonsfirstpyapp-0.0.2.dist-info/top_level.txt
ryanjohnsonsfirstpyapp-0.0.2.dist-info/RECORD
